pyEliasFano/EliasFano.py
pyEliasFano/UniformlyPartitionedEliasFano.py
pyEliasFano/__init__.py
pyEliasFano-0.0.8.dist-info/LICENSE
pyEliasFano-0.0.8.dist-info/METADATA
pyEliasFano-0.0.8.dist-info/WHEEL
pyEliasFano-0.0.8.dist-info/top_level.txt
pyEliasFano-0.0.8.dist-info/RECORD
