Metadata-Version: 2.1
Name: pyEliasFano
Version: 0.0.8
Summary: pyEliasFano offers quasi-succinct represenations for monotone non-decreasing sequences of integers.
Home-page: https://github.com/rmrschub/pyEliasFano
Author: René Schubotz
Author-email: rene.schubotz@dfki.de
License: CC BY-NC-SA 4.0
Platform: UNKNOWN
License-File: LICENSE
Requires-Dist: typing
Requires-Dist: numpy
Requires-Dist: bitarray
